[
  {
    "CoinTaken": [],
    "CoinUsed": [],
    "x": 0.0,
    "y": 0.0,
    "z": 0.0,
    "x_rot": 0.0,
    "y_rot": 0.0,
    "z_rot": 0.0,
    "w_rot": 0.0,
    "CameraRot_X": 0.0,
    "CameraRot_Y": 0.0,
    "Name": "1",
    "Date": "2024-08-07T12:37:23.8644179+08:00",
    "Level": 3,
    "Count": 0.0,
    "IsTimerRun": false
  },
  {
    "CoinTaken": [],
    "CoinUsed": [],
    "x": 0.0,
    "y": 0.0,
    "z": 0.0,
    "x_rot": 0.0,
    "y_rot": 0.0,
    "z_rot": 0.0,
    "w_rot": 0.0,
    "CameraRot_X": 0.0,
    "CameraRot_Y": 0.0,
    "Name": "2",
    "Date": "2024-08-07T12:56:44.7959244+08:00",
    "Level": 3,
    "Count": 0.0,
    "IsTimerRun": false
  },
  {
    "CoinTaken": [],
    "CoinUsed": [],
    "x": 0.0,
    "y": 0.0,
    "z": 0.0,
    "x_rot": 0.0,
    "y_rot": 0.0,
    "z_rot": 0.0,
    "w_rot": 0.0,
    "CameraRot_X": 0.0,
    "CameraRot_Y": 0.0,
    "Name": "3",
    "Date": "2024-08-07T13:18:27.7305254+08:00",
    "Level": 3,
    "Count": 0.0,
    "IsTimerRun": false
  },
  {
    "CoinTaken": [],
    "CoinUsed": [],
    "x": 0.0,
    "y": 0.0,
    "z": 0.0,
    "x_rot": 0.0,
    "y_rot": 0.0,
    "z_rot": 0.0,
    "w_rot": 0.0,
    "CameraRot_X": 0.0,
    "CameraRot_Y": 0.0,
    "Name": "4",
    "Date": "2024-08-07T13:19:44.7725074+08:00",
    "Level": 3,
    "Count": 0.0,
    "IsTimerRun": false
  },
  {
    "CoinTaken": [],
    "CoinUsed": [],
    "x": 0.0,
    "y": 0.0,
    "z": 0.0,
    "x_rot": 0.0,
    "y_rot": 0.0,
    "z_rot": 0.0,
    "w_rot": 0.0,
    "CameraRot_X": 0.0,
    "CameraRot_Y": 0.0,
    "Name": "5",
    "Date": "2024-08-09T13:26:30.3987196+08:00",
    "Level": 3,
    "Count": 0.0,
    "IsTimerRun": false
  }
]